EmojiStore/__init__.py
EmojiStore/emojis.py
EmojiStore/storage.py
EmojiStore-1.0.2.dist-info/LICENSE
EmojiStore-1.0.2.dist-info/METADATA
EmojiStore-1.0.2.dist-info/WHEEL
EmojiStore-1.0.2.dist-info/top_level.txt
EmojiStore-1.0.2.dist-info/RECORD
