Metadata-Version: 2.1
Name: EmojiStore
Version: 1.0.2
Summary: Free unicode emojis ready to use !
Home-page: https://antaresmugisho.vercel.app/
Download-URL: https://github.com/AntaresMugisho/EmojiStore/archive/refs/tags/v1.0-beta.tar.gz
Author: Antares Mugisho
Author-email: antaresmugisho@gmail.com
License: MIT
Keywords: python,emoji,sticker,mood
Classifier: Development Status :: 4 - Beta
Classifier: Intended Audience :: Developers
Classifier: Topic :: Software Development :: Build Tools
Classifier: License :: OSI Approved :: MIT License
Classifier: Operating System :: OS Independent
Classifier: Programming Language :: Python :: 3
Classifier: Programming Language :: Python :: 3.9
Classifier: Programming Language :: Python :: 3.10
Classifier: Programming Language :: Python :: 3.11
License-File: LICENSE
